{
    "ЮЛ": {
        "ИНН": "6679099985",
        "КПП": "667901001",
        "ОГРН": "1169658112062",
        "ДатаОГРН": "2016-09-30",
        "ДатаРег": "2016-09-30",
        "ОКОПФ": "Общества с ограниченной ответственностью",
        "КодОКОПФ": "12300",
        "Статус": "Действующее",
        "СпОбрЮЛ": "Создание юридического лица",
        "НО": {
            "Рег": "6658 (Инспекция Федеральной налоговой службы по Верх-Исетскому району г.Екатеринбурга)",
            "РегДата": "2016-09-30",
            "Учет": "6679 (Межрайонная инспекция Федеральной налоговой службы №25 по Свердловской области)",
            "УчетДата": "2016-09-30"
        },
        "ПФ": {
            "РегНомПФ": "1043315231",
            "ДатаРегПФ": "2016-10-03",
            "КодПФ": "066 (Отделение Фонда пенсионного и социального страхования Российской Федерации по Свердловской области)"
        },
        "ФСС": {
            "РегНомФСС": "1043315231",
            "ДатаРегФСС": "2016-10-03",
            "КодФСС": "066 (Отделение Фонда пенсионного и социального страхования Российской Федерации по Свердловской области)"
        },
        "КодыСтат": {
            "ОКПО": "0004831689",
            "ОКТМО": "65754000001",
            "ОКФС": "16",
            "ОКОГУ": "4210014"
        },
        "Капитал": {
            "ВидКап": "Уставный капитал",
            "СумКап": "1000000",
            "Дата": "2018-03-12"
        },
        "НаимСокрЮЛ": "ООО ПК \"САЙВЕРХОТ\"",
        "НаимПолнЮЛ": "ОБЩЕСТВО С ОГРАНИЧЕННОЙ ОТВЕТСТВЕННОСТЬЮ ПРОИЗВОДСТВЕННЫЙ КОМПЛЕКС \"САЙВЕРХОТ\"",
        "Адрес": {
            "КодРегион": "66",
            "КодКЛАДР": "660000170000197",
            "Индекс": "623391",
            "АдресПолн": "обл. Свердловская, г. Полевской, р-н Восточный Промышленный, зд.6/3",
            "АдресДетали": {
                "Регион": {
                    "Тип": "ОБЛАСТЬ",
                    "Наим": "СВЕРДЛОВСКАЯ"
                },
                "Город": {
                    "Тип": "ГОРОД",
                    "Наим": "ПОЛЕВСКОЙ"
                },
                "Район": {
                    "Тип": "РАЙОН",
                    "Наим": "ВОСТОЧНЫЙ ПРОМЫШЛЕННЫЙ"
                },
                "Дом": "ЗДАНИЕ 6/3"
            },
            "Дата": "2018-04-13"
        },
        "Руководитель": {
            "ВидДолжн": "Руководитель юридического лица",
            "Должн": "Генеральный директор",
            "ФИОПолн": "Сазонов Виталий Геннадьевич",
            "ИННФЛ": "662606794712",
            "Пол": "Мужской",
            "ВидГражд": "Гражданин РФ",
            "Дата": "2016-09-30"
        },
        "Учредители": [
            {
                "УчрФЛ": {
                    "ФИОПолн": "Сазонов Виталий Геннадьевич",
                    "ИННФЛ": "662606794712",
                    "Пол": "Мужской",
                    "ВидГражд": "Гражданин РФ"
                },
                "СуммаУК": "1000000",
                "Процент": "100",
                "Дата": "2018-03-12"
            }
        ],
        "Контакты": {
            "Телефон": [
                "+73433046026",
                "+73433832698",
                "+79222007757",
                "+79222266907",
                "+78005502697",
                "+79221598370",
                "+73817021861"
            ],
            "e-mail": [
                "i.makarov@saverhot.ru",
                "st4@saverhot.ru",
                "tender2@saverhot.ru",
                "info@saverhot.ru",
                "tender@saverhot.ru",
                "eco09@mail.ru"
            ]
        },
        "ОснВидДеят": {
            "Код": "25.61",
            "Текст": "Обработка металлов и нанесение покрытий на металлы",
            "Дата": "2016-09-30"
        },
        "ДопВидДеят": [
            {
                "Код": "23.99.6",
                "Текст": "Производство минеральных тепло- и звукоизоляционных материалов и изделий",
                "Дата": "2016-09-30"
            },
            {
                "Код": "24.20",
                "Текст": "Производство стальных труб, полых профилей и фитингов",
                "Дата": "2016-09-30"
            },
            {
                "Код": "25.62",
                "Текст": "Обработка металлических изделий механическая",
                "Дата": "2016-09-30"
            },
            {
                "Код": "46.72.2",
                "Текст": "Торговля оптовая металлами в первичных формах",
                "Дата": "2016-09-30"
            },
            {
                "Код": "46.74.2",
                "Текст": "Торговля оптовая водопроводным и отопительным оборудованием и санитарно-технической арматурой",
                "Дата": "2016-09-30"
            },
            {
                "Код": "49.41.2",
                "Текст": "Перевозка грузов неспециализированными автотранспортными средствами",
                "Дата": "2016-09-30"
            },
            {
                "Код": "68.20.2",
                "Текст": "Аренда и управление собственным или арендованным нежилым недвижимым имуществом",
                "Дата": "2016-09-30"
            }
        ],
        "СПВЗ": [
            {
                "Дата": "2025-01-28",
                "Текст": "Представление сведений о регистрации юридического лица в качестве страхователя в Социальном фонде Российской Федерации (обязательное социальное страхование)"
            },
            {
                "Дата": "2025-01-28",
                "Текст": "Представление сведений о регистрации юридического лица в качестве страхователя в Социальном фонде Российской Федерации (обязательное пенсионное страхование)"
            },
            {
                "Дата": "2025-01-17",
                "Текст": "Внесение изменений в сведения, содержащиеся в Едином государственном реестре юридических лиц, в связи с переименованием (переподчинением) адресных объектов"
            },
            {
                "Дата": "2024-04-23",
                "Текст": "Представление лицензирующим органом сведений о переоформлении лицензии, внесении изменений в сведения о лицензии (сведений о продлении срока действия лицензии)"
            },
            {
                "Дата": "2024-02-05",
                "Текст": "Внесение изменений в сведения, содержащиеся в Едином государственном реестре юридических лиц, в связи с переименованием (переподчинением) адресных объектов"
            },
            {
                "Дата": "2024-02-04",
                "Текст": "Внесение изменений в сведения, содержащиеся в Едином государственном реестре юридических лиц, в связи с переименованием (переподчинением) адресных объектов"
            },
            {
                "Дата": "2022-11-17",
                "Текст": "Представление сведений о регистрации физического лица по месту жительства"
            },
            {
                "Дата": "2022-11-17",
                "Текст": "Представление сведений о регистрации физического лица по месту жительства"
            },
            {
                "Дата": "2019-06-27",
                "Текст": "Представление лицензирующим органом сведений о предоставлении лицензии"
            },
            {
                "Дата": "2018-04-13",
                "Текст": "Внесение изменений в сведения, содержащиеся в Едином государственном реестре юридических лиц, в связи с переименованием (переподчинением) адресных объектов"
            },
            {
                "Дата": "2018-03-12",
                "Текст": "Государственная регистрация изменений, внесенных в учредительный документ юридического лица, и внесение изменений в сведения о юридическом лице, содержащиеся в ЕГРЮЛ"
            },
            {
                "Дата": "2017-06-22",
                "Текст": "Изменение сведений о юридическом лице, содержащихся в Едином государственном реестре юридических лиц"
            },
            {
                "Дата": "2016-10-06",
                "Текст": "Представление сведений о регистрации юридического лица в качестве страхователя в исполнительном органе Фонда социального страхования Российской Федерации"
            },
            {
                "Дата": "2016-10-04",
                "Текст": "Представление сведений о регистрации юридического лица в качестве страхователя в территориальном органе Пенсионного фонда Российской Федерации"
            },
            {
                "Дата": "2016-09-30",
                "Текст": "Представление сведений об учете юридического лица в налоговом органе"
            },
            {
                "Дата": "2016-09-30",
                "Текст": "Создание юридического лица"
            }
        ],
        "ОткрСведения": {
            "КолРаб": "165",
            "СведСНР": "Нет",
            "ПризнУчКГН": "Нет",
            "СумДоход": "2842773000",
            "СумРасход": "2614336000",
            "Дата": "2025-01-01"
        },
        "Лицензии": [
            {
                "НомерЛиц": "АН 66-001220",
                "ВидДеятельности": "Деятельность по перевозкам пассажиров и иных лиц автобусами",
                "ДатаЛиц": "2019-06-27",
                "ДатаНачала": "2019-06-27",
                "ЛицОрг": "МЕЖРЕГИОНАЛЬНОЕ ТЕРРИТОРИАЛЬНОЕ УПРАВЛЕНИЕ ФЕДЕРАЛЬНОЙ СЛУЖБЫ ПО НАДЗОРУ В СФЕРЕ ТРАНСПОРТА ПО УРАЛЬСКОМУ ФЕДЕРАЛЬНОМУ ОКРУГУ"
            }
        ],
        "История": {
            "Капитал": {
                "2016-09-30 ~ 2018-03-11": {
                    "СумКап": "10000"
                }
            },
            "E-mail": {
                "2016-09-30 ~ 2017-06-21": "E.SKORNYAKOVA@INTELLECTMAIL.RU"
            },
            "Адрес": {
                "2016-09-30 ~ 2018-04-12": {
                    "АдресПолн": "обл. Свердловская, г. Полевской, тер. Восточный Промышленный Район, д.6, кор.3"
                }
            },
            "Участия": [
                {
                    "ОГРН": "1169658112062",
                    "ИНН": "6679099985",
                    "НаимСокрЮЛ": "ООО ПК \"САЙВЕРХОТ\"",
                    "НаимПолнЮЛ": "ООО ПРОИЗВОДСТВЕННЫЙ КОМПЛЕКС \"САЙВЕРХОТ\"",
                    "Статус": "Действующее",
                    "ДатаОконч": "2018-03-11"
                }
            ],
            "Учредители": [
                {
                    "УчрФЛ": {
                        "ФИОПолн": "Киселев Иван Владимирович",
                        "ИННФЛ": "662603286358"
                    },
                    "СуммаУК": "5000",
                    "Процент": "50",
                    "Дата": "2016-09-30",
                    "ДатаОконч": "2017-06-21"
                },
                {
                    "УчрФЛ": {
                        "ФИОПолн": "Сазонов Виталий Геннадьевич",
                        "ИННФЛ": "662606794712",
                        "Пол": "Мужской",
                        "ВидГражд": "Гражданин РФ"
                    },
                    "СуммаУК": "5000",
                    "Процент": "50",
                    "Дата": "2016-09-30",
                    "ДатаОконч": "2017-06-21"
                },
                {
                    "УчрФЛ": {
                        "ФИОПолн": "Сазонов Виталий Геннадьевич",
                        "ИННФЛ": "662606794712",
                        "Пол": "Мужской",
                        "ВидГражд": "Гражданин РФ"
                    },
                    "СуммаУК": "10000",
                    "Процент": "100",
                    "Дата": "2017-06-22",
                    "ДатаОконч": "2018-03-11"
                },
                {
                    "УчрЮЛ": {
                        "ОГРН": "1169658112062",
                        "ИНН": "6679099985",
                        "НаимСокрЮЛ": "ООО ПК \"САЙВЕРХОТ\"",
                        "Статус": "Действующее"
                    },
                    "Дата": "2017-06-22",
                    "ДатаОконч": "2018-03-11"
                }
            ],
            "ОткрСведения": [
                {
                    "КолРаб": "4",
                    "СведСНР": "Нет",
                    "ПризнУчКГН": "Нет",
                    "Налоги": [
                        {
                            "НаимНалог": "Страховые взносы на обязательное медицинское страхование работающего населения, зачисляемые в бюджет Федерального фонда обязательного медицинского страхования",
                            "СумУплНал": "59320.96"
                        },
                        {
                            "НаимНалог": "Страховые и другие взносы на обязательное пенсионное страхование, зачисляемые в Пенсионный фонд Российской Федерации",
                            "СумУплНал": "255894.36"
                        },
                        {
                            "НаимНалог": "Страховые взносы на обязательное социальное страхование на случай временной нетрудоспособности и в связи с материнством",
                            "СумУплНал": "33791.52"
                        },
                        {
                            "НаимНалог": "Налог на добавленную стоимость",
                            "СумУплНал": "486772"
                        },
                        {
                            "НаимНалог": "Налог на прибыль",
                            "СумУплНал": "1334700"
                        },
                        {
                            "НаимНалог": "Транспортный налог",
                            "СумУплНал": "0"
                        },
                        {
                            "НаимНалог": "Налог на имущество организаций",
                            "СумУплНал": "0"
                        },
                        {
                            "НаимНалог": "Неналоговые доходы, администрируемые налоговыми органами",
                            "СумУплНал": "0"
                        }
                    ],
                    "СумДоход": "473093000",
                    "СумРасход": "452594000",
                    "ОтраслевыеПок": {
                        "НалогНагрузка": "0.043",
                        "Рентабельность": "0.107"
                    },
                    "Дата": "2018-01-01"
                },
                {
                    "КолРаб": "25",
                    "СведСНР": "Нет",
                    "ПризнУчКГН": "Нет",
                    "Налоги": [
                        {
                            "НаимНалог": "Страховые взносы на обязательное медицинское страхование работающего населения, зачисляемые в бюджет Федерального фонда обязательного медицинского страхования",
                            "СумУплНал": "430002.34",
                            "СумНедНалог": "0",
                            "СумПени": "10.08",
                            "СумШтраф": "0",
                            "ОбщСумНедоим": "10.08"
                        },
                        {
                            "НаимНалог": "Страховые и другие взносы на обязательное пенсионное страхование, зачисляемые в Пенсионный фонд Российской Федерации",
                            "СумУплНал": "1854912.07",
                            "СумНедНалог": "0",
                            "СумПени": "43.46",
                            "СумШтраф": "0",
                            "ОбщСумНедоим": "43.46"
                        },
                        {
                            "НаимНалог": "Страховые взносы на обязательное социальное страхование на случай временной нетрудоспособности и в связи с материнством",
                            "СумУплНал": "186768.37",
                            "СумНедНалог": "0",
                            "СумПени": "5.38",
                            "СумШтраф": "0",
                            "ОбщСумНедоим": "5.38"
                        },
                        {
                            "НаимНалог": "Налог на добавленную стоимость",
                            "СумУплНал": "1958966"
                        },
                        {
                            "НаимНалог": "Налог на прибыль",
                            "СумУплНал": "3810852",
                            "СумНедНалог": "0",
                            "СумПени": "54024.76",
                            "СумШтраф": "0",
                            "ОбщСумНедоим": "54024.76"
                        },
                        {
                            "НаимНалог": "Транспортный налог",
                            "СумУплНал": "939"
                        },
                        {
                            "НаимНалог": "Налог на имущество организаций",
                            "СумУплНал": "274087",
                            "СумНедНалог": "0",
                            "СумПени": "14.63",
                            "СумШтраф": "0",
                            "ОбщСумНедоим": "14.63"
                        },
                        {
                            "НаимНалог": "Неналоговые доходы, администрируемые налоговыми органами",
                            "СумУплНал": "0"
                        }
                    ],
                    "СумДоход": "673236000",
                    "СумРасход": "666515000",
                    "ОтраслевыеПок": {
                        "НалогНагрузка": "0.041",
                        "Рентабельность": "0.117"
                    },
                    "Дата": "2019-01-01"
                },
                {
                    "КолРаб": "55",
                    "СведСНР": "Нет",
                    "ПризнУчКГН": "Нет",
                    "Налоги": [
                        {
                            "НаимНалог": "Страховые взносы на обязательное медицинское страхование работающего населения, зачисляемые в бюджет Федерального фонда обязательного медицинского страхования",
                            "СумУплНал": "1408607.64"
                        },
                        {
                            "НаимНалог": "Страховые и другие взносы на обязательное пенсионное страхование, зачисляемые в Пенсионный фонд Российской Федерации",
                            "СумУплНал": "6076346.75"
                        },
                        {
                            "НаимНалог": "Страховые взносы на обязательное социальное страхование на случай временной нетрудоспособности и в связи с материнством",
                            "СумУплНал": "547203.86"
                        },
                        {
                            "НаимНалог": "Налог на добавленную стоимость",
                            "СумУплНал": "1948370"
                        },
                        {
                            "НаимНалог": "Налог на прибыль",
                            "СумУплНал": "0"
                        },
                        {
                            "НаимНалог": "Транспортный налог",
                            "СумУплНал": "26630"
                        },
                        {
                            "НаимНалог": "Налог на имущество организаций",
                            "СумУплНал": "210286"
                        },
                        {
                            "НаимНалог": "Неналоговые доходы, администрируемые налоговыми органами",
                            "СумУплНал": "0"
                        }
                    ],
                    "СумДоход": "688504000",
                    "СумРасход": "675765000",
                    "ОтраслевыеПок": {
                        "НалогНагрузка": "0.04",
                        "Рентабельность": "0.102"
                    },
                    "Дата": "2020-01-01"
                },
                {
                    "КолРаб": "83",
                    "СведСНР": "Нет",
                    "ПризнУчКГН": "Нет",
                    "Налоги": [
                        {
                            "НаимНалог": "Страховые взносы на обязательное медицинское страхование работающего населения, зачисляемые в бюджет Федерального фонда обязательного медицинского страхования",
                            "СумУплНал": "2156266.04"
                        },
                        {
                            "НаимНалог": "Страховые и другие взносы на обязательное пенсионное страхование, зачисляемые в Пенсионный фонд Российской Федерации",
                            "СумУплНал": "6832351.14"
                        },
                        {
                            "НаимНалог": "Страховые взносы на обязательное социальное страхование на случай временной нетрудоспособности и в связи с материнством",
                            "СумУплНал": "326710.13"
                        },
                        {
                            "НаимНалог": "Налог на добавленную стоимость",
                            "СумУплНал": "16809864"
                        },
                        {
                            "НаимНалог": "Налог на прибыль",
                            "СумУплНал": "5828524.24"
                        },
                        {
                            "НаимНалог": "Транспортный налог",
                            "СумУплНал": "180721"
                        },
                        {
                            "НаимНалог": "Налог на имущество организаций",
                            "СумУплНал": "0"
                        },
                        {
                            "НаимНалог": "Неналоговые доходы, администрируемые налоговыми органами",
                            "СумУплНал": "0"
                        }
                    ],
                    "СумДоход": "1362577000",
                    "СумРасход": "1303947000",
                    "ОтраслевыеПок": {
                        "НалогНагрузка": "0.034299122",
                        "Рентабельность": "0.119"
                    },
                    "Дата": "2021-01-01"
                },
                {
                    "КолРаб": "102",
                    "СведСНР": "Нет",
                    "ПризнУчКГН": "Нет",
                    "Налоги": [
                        {
                            "НаимНалог": "Страховые взносы на обязательное медицинское страхование работающего населения, зачисляемые в бюджет Федерального фонда обязательного медицинского страхования",
                            "СумУплНал": "2697680.46"
                        },
                        {
                            "НаимНалог": "Страховые и другие взносы на обязательное пенсионное страхование, зачисляемые в Пенсионный фонд Российской Федерации",
                            "СумУплНал": "7257882.58"
                        },
                        {
                            "НаимНалог": "Страховые взносы на обязательное социальное страхование на случай временной нетрудоспособности и в связи с материнством",
                            "СумУплНал": "0"
                        },
                        {
                            "НаимНалог": "Налог на добавленную стоимость",
                            "СумУплНал": "4754869"
                        },
                        {
                            "НаимНалог": "Налог на прибыль",
                            "СумУплНал": "11007191"
                        },
                        {
                            "НаимНалог": "Транспортный налог",
                            "СумУплНал": "196526"
                        },
                        {
                            "НаимНалог": "Налог на имущество организаций",
                            "СумУплНал": "0"
                        },
                        {
                            "НаимНалог": "Неналоговые доходы, администрируемые налоговыми органами",
                            "СумУплНал": "0"
                        }
                    ],
                    "СумДоход": "1884098000",
                    "СумРасход": "1813836000",
                    "ОтраслевыеПок": {
                        "НалогНагрузка": "0.048",
                        "Рентабельность": "0.112"
                    },
                    "Дата": "2022-01-01"
                },
                {
                    "КолРаб": "141",
                    "СведСНР": "Нет",
                    "ПризнУчКГН": "Нет",
                    "Налоги": [
                        {
                            "НаимНалог": "Страховые взносы на обязательное медицинское страхование работающего населения, зачисляемые в бюджет Федерального фонда обязательного медицинского страхования",
                            "СумУплНал": "2147878.58"
                        },
                        {
                            "НаимНалог": "Страховые и другие взносы на обязательное пенсионное страхование, зачисляемые в Пенсионный фонд Российской Федерации",
                            "СумУплНал": "5701255.05"
                        },
                        {
                            "НаимНалог": "Страховые взносы на обязательное социальное страхование на случай временной нетрудоспособности и в связи с материнством",
                            "СумУплНал": "257093.36"
                        },
                        {
                            "НаимНалог": "Налог на добавленную стоимость",
                            "СумУплНал": "21490711.83"
                        },
                        {
                            "НаимНалог": "Налог на прибыль",
                            "СумУплНал": "17312290"
                        },
                        {
                            "НаимНалог": "Транспортный налог",
                            "СумУплНал": "223305"
                        },
                        {
                            "НаимНалог": "Налог на имущество организаций",
                            "СумУплНал": "0"
                        },
                        {
                            "НаимНалог": "Неналоговые доходы, администрируемые налоговыми органами",
                            "СумУплНал": "0"
                        }
                    ],
                    "СумДоход": "2114845000",
                    "СумРасход": "1959422000",
                    "ОтраслевыеПок": {
                        "НалогНагрузка": "0.037440019",
                        "Рентабельность": "0.1"
                    },
                    "Дата": "2023-01-01"
                },
                {
                    "КолРаб": "167",
                    "СведСНР": "Нет",
                    "ПризнУчКГН": "Нет",
                    "Налоги": [
                        {
                            "НаимНалог": "Страховые взносы на обязательное медицинское страхование работающего населения, зачисляемые в бюджет Федерального фонда обязательного медицинского страхования",
                            "СумУплНал": "1345226.97"
                        },
                        {
                            "НаимНалог": "Страховые и другие взносы на обязательное пенсионное страхование, зачисляемые в Пенсионный фонд Российской Федерации",
                            "СумУплНал": "28902561.19"
                        },
                        {
                            "НаимНалог": "Страховые взносы на обязательное социальное страхование на случай временной нетрудоспособности и в связи с материнством",
                            "СумУплНал": "169940"
                        },
                        {
                            "НаимНалог": "Налог на добавленную стоимость",
                            "СумУплНал": "4559129.17"
                        },
                        {
                            "НаимНалог": "Налог на прибыль",
                            "СумУплНал": "40333635.21"
                        },
                        {
                            "НаимНалог": "Транспортный налог",
                            "СумУплНал": "348945"
                        },
                        {
                            "НаимНалог": "Налог на имущество организаций",
                            "СумУплНал": "47885"
                        },
                        {
                            "НаимНалог": "Земельный налог",
                            "СумУплНал": "3101"
                        },
                        {
                            "НаимНалог": "Неналоговые доходы, администрируемые налоговыми органами",
                            "СумУплНал": "0"
                        },
                        {
                            "НаимНалог": "Суммы пеней",
                            "СумУплНал": "375913.46"
                        }
                    ],
                    "СумДоход": "3161899000",
                    "СумРасход": "2861878000",
                    "ОтраслевыеПок": {
                        "НалогНагрузка": "0.07",
                        "Рентабельность": "0.169"
                    },
                    "Дата": "2024-01-01"
                },
                {
                    "СведСНР": "Нет",
                    "ПризнУчКГН": "Нет",
                    "Налоги": [
                        {
                            "НаимНалог": "Налог на добавленную стоимость",
                            "СумНедНалог": "13101",
                            "СумПени": "0",
                            "СумШтраф": "0",
                            "ОбщСумНедоим": "13101"
                        },
                        {
                            "НаимНалог": "Налог на прибыль",
                            "СумНедНалог": "3314903",
                            "СумПени": "0",
                            "СумШтраф": "0",
                            "ОбщСумНедоим": "3314903"
                        },
                        {
                            "НаимНалог": "Налог на доходы физических лиц",
                            "СумНедНалог": "1329401",
                            "СумПени": "0",
                            "СумШтраф": "0",
                            "ОбщСумНедоим": "1329401"
                        },
                        {
                            "НаимНалог": "Страховые взносы",
                            "СумНедНалог": "4384333.51",
                            "СумПени": "0",
                            "СумШтраф": "0",
                            "ОбщСумНедоим": "4384333.51"
                        },
                        {
                            "НаимНалог": "Суммы пеней",
                            "СумНедНалог": "0",
                            "СумПени": "131436.3",
                            "СумШтраф": "0",
                            "ОбщСумНедоим": "131436.3"
                        }
                    ],
                    "Дата": "2024-02-11"
                },
                {
                    "СведСНР": "Нет",
                    "ПризнУчКГН": "Нет",
                    "Налоги": [
                        {
                            "НаимНалог": "Налог на добавленную стоимость",
                            "СумНедНалог": "106748",
                            "СумПени": "0",
                            "СумШтраф": "0",
                            "ОбщСумНедоим": "106748"
                        },
                        {
                            "НаимНалог": "Налог на прибыль",
                            "СумНедНалог": "12993648.21",
                            "СумПени": "0",
                            "СумШтраф": "0",
                            "ОбщСумНедоим": "12993648.21"
                        },
                        {
                            "НаимНалог": "Налог на имущество организаций",
                            "СумНедНалог": "138741",
                            "СумПени": "0",
                            "СумШтраф": "0",
                            "ОбщСумНедоим": "138741"
                        },
                        {
                            "НаимНалог": "Земельный налог",
                            "СумНедНалог": "23262",
                            "СумПени": "0",
                            "СумШтраф": "0",
                            "ОбщСумНедоим": "23262"
                        },
                        {
                            "НаимНалог": "Налог на доходы физических лиц",
                            "СумНедНалог": "1853033",
                            "СумПени": "0",
                            "СумШтраф": "0",
                            "ОбщСумНедоим": "1853033"
                        },
                        {
                            "НаимНалог": "Страховые взносы",
                            "СумНедНалог": "5072966.48",
                            "СумПени": "0",
                            "СумШтраф": "0",
                            "ОбщСумНедоим": "5072966.48"
                        },
                        {
                            "НаимНалог": "Суммы пеней",
                            "СумНедНалог": "0",
                            "СумПени": "537577.36",
                            "СумШтраф": "0",
                            "ОбщСумНедоим": "537577.36"
                        }
                    ],
                    "Дата": "2024-05-11"
                }
            ]
        }
    }
}