{
    "ЮЛ": {
        "ИНН": "7448159452",
        "КПП": "745301001",
        "ОГРН": "1137448005969",
        "ДатаОГРН": "2013-05-29",
        "ДатаРег": "2013-05-29",
        "ОКОПФ": "Общества с ограниченной ответственностью",
        "КодОКОПФ": "12300",
        "Статус": "Действующее",
        "СпОбрЮЛ": "Создание юридического лица",
        "НО": {
            "Рег": "7456 (Межрайонная инспекция Федеральной налоговой службы № 17 по Челябинской области)",
            "РегДата": "2015-12-21",
            "Учет": "7453 (Межрайонная инспекция Федеральной налоговой службы № 28 по Челябинской области)",
            "УчетДата": "2019-08-01"
        },
        "ПФ": {
            "РегНомПФ": "1070148422",
            "ДатаРегПФ": "2019-08-05",
            "КодПФ": "074 (Отделение Фонда пенсионного и социального страхования Российской Федерации по Челябинской области)"
        },
        "ФСС": {
            "РегНомФСС": "1070148422",
            "ДатаРегФСС": "2019-08-02",
            "КодФСС": "074 (Отделение Фонда пенсионного и социального страхования Российской Федерации по Челябинской области)"
        },
        "КодыСтат": {
            "ОКПО": "0021609679",
            "ОКТМО": "75701390000",
            "ОКФС": "16",
            "ОКОГУ": "4210014"
        },
        "Капитал": {
            "ВидКап": "Уставный капитал",
            "СумКап": "10000",
            "Дата": "2013-05-29"
        },
        "НаимСокрЮЛ": "ООО ТОРГОВЫЙ ХОЛДИНГ \"АТЛАНТИК\"",
        "НаимПолнЮЛ": "ОБЩЕСТВО С ОГРАНИЧЕННОЙ ОТВЕТСТВЕННОСТЬЮ  ТОРГОВЫЙ ХОЛДИНГ \"АТЛАНТИК\"",
        "Адрес": {
            "КодРегион": "74",
            "КодКЛАДР": "740000010000478",
            "Индекс": "454080",
            "АдресПолн": "обл. Челябинская, г. Челябинск, ул. Сони Кривой, д.43А, пом.103",
            "АдресДетали": {
                "Регион": {
                    "Тип": "ОБЛАСТЬ",
                    "Наим": "ЧЕЛЯБИНСКАЯ"
                },
                "Город": {
                    "Тип": "ГОРОД",
                    "Наим": "ЧЕЛЯБИНСК"
                },
                "Улица": {
                    "Тип": "УЛИЦА",
                    "Наим": "СОНИ КРИВОЙ"
                },
                "Дом": "ДОМ 43А",
                "Помещ": "ПОМЕЩЕНИЕ 103"
            },
            "Дата": "2019-08-01"
        },
        "Руководитель": {
            "ВидДолжн": "Руководитель юридического лица",
            "Должн": "Генеральный директор",
            "ФИОПолн": "Будник Павел Владимирович",
            "ИННФЛ": "744903252089",
            "Пол": "Мужской",
            "ВидГражд": "Гражданин РФ",
            "Дата": "2020-03-27"
        },
        "Учредители": [
            {
                "УчрФЛ": {
                    "ФИОПолн": "Будник Павел Владимирович",
                    "ИННФЛ": "744903252089",
                    "Пол": "Мужской",
                    "ВидГражд": "Гражданин РФ"
                },
                "СуммаУК": "10000",
                "Процент": "100",
                "Дата": "2016-08-17"
            }
        ],
        "Контакты": {
            "Телефон": [
                "+73512645044",
                "+73512645125",
                "+73512645181",
                "+73512645205",
                "+73512645264"
            ],
            "e-mail": [
                "td-atlantik@yandex.ru",
                "direktor@td-atlantiкmail.ru"
            ],
            "Сайт": [
                "th-atlantik.ru"
            ]
        },
        "ОснВидДеят": {
            "Код": "46.90",
            "Текст": "Торговля оптовая неспециализированная",
            "Дата": "2013-05-29"
        },
        "ДопВидДеят": [
            {
                "Код": "13.30.5",
                "Текст": "Нанесение рисунка на текстильные изделия и готовую одежду",
                "Дата": "2022-11-18"
            },
            {
                "Код": "14.12",
                "Текст": "Производство спецодежды",
                "Дата": "2022-11-18"
            },
            {
                "Код": "14.13",
                "Текст": "Производство прочей верхней одежды",
                "Дата": "2022-11-18"
            },
            {
                "Код": "14.14",
                "Текст": "Производство нательного белья",
                "Дата": "2022-11-18"
            },
            {
                "Код": "46.11.39",
                "Текст": "Деятельность агентов по оптовой торговле прочими сельскохозяйственным сырьем и сельскохозяйственными полуфабрикатами, не включенными в другие группировки",
                "Дата": "2013-05-29"
            },
            {
                "Код": "46.42",
                "Текст": "Торговля оптовая одеждой и обувью",
                "Дата": "2022-11-18"
            },
            {
                "Код": "46.71",
                "Текст": "Торговля оптовая твердым, жидким и газообразным топливом и подобными продуктами",
                "Дата": "2023-05-15"
            },
            {
                "Код": "46.71.1",
                "Текст": "Торговля оптовая твердым топливом",
                "Дата": "2023-05-15"
            },
            {
                "Код": "46.71.2",
                "Текст": "Торговля оптовая моторным топливом, включая авиационный бензин",
                "Дата": "2023-05-15"
            },
            {
                "Код": "46.71.9",
                "Текст": "Торговля оптовая прочим топливом и подобными продуктами",
                "Дата": "2023-05-15"
            },
            {
                "Код": "47.11.1",
                "Текст": "Торговля розничная замороженными продуктами в неспециализированных магазинах",
                "Дата": "2013-05-29"
            },
            {
                "Код": "47.11.2",
                "Текст": "Торговля розничная незамороженными продуктами, включая напитки и табачные изделия, в неспециализированных магазинах",
                "Дата": "2013-05-29"
            },
            {
                "Код": "47.19",
                "Текст": "Торговля розничная прочая в неспециализированных магазинах",
                "Дата": "2013-05-29"
            },
            {
                "Код": "47.71",
                "Текст": "Торговля розничная одеждой в специализированных магазинах",
                "Дата": "2022-11-18"
            },
            {
                "Код": "47.72",
                "Текст": "Торговля розничная обувью и изделиями из кожи в специализированных магазинах",
                "Дата": "2022-11-18"
            },
            {
                "Код": "47.78",
                "Текст": "Торговля розничная прочая в специализированных магазинах",
                "Дата": "2013-05-29"
            },
            {
                "Код": "47.9",
                "Текст": "Торговля розничная вне магазинов, палаток, рынков",
                "Дата": "2013-05-29"
            },
            {
                "Код": "47.99",
                "Текст": "Торговля розничная прочая вне магазинов, палаток, рынков",
                "Дата": "2013-05-29"
            },
            {
                "Код": "68.32",
                "Текст": "Управление недвижимым имуществом за вознаграждение или на договорной основе",
                "Дата": "2023-10-05"
            }
        ],
        "СПВЗ": [
            {
                "Дата": "2025-02-14",
                "Текст": "Внесение изменений в сведения, содержащиеся в Едином государственном реестре юридических лиц, в связи с переименованием (переподчинением) адресных объектов"
            },
            {
                "Дата": "2025-02-01",
                "Текст": "Представление сведений о регистрации юридического лица в качестве страхователя в Социальном фонде Российской Федерации (обязательное пенсионное страхование)"
            },
            {
                "Дата": "2025-02-01",
                "Текст": "Представление сведений о регистрации юридического лица в качестве страхователя в Социальном фонде Российской Федерации (обязательное социальное страхование)"
            },
            {
                "Дата": "2023-10-05",
                "Текст": "Изменение сведений о юридическом лице, содержащихся в Едином государственном реестре юридических лиц"
            },
            {
                "Дата": "2023-05-15",
                "Текст": "Изменение сведений о юридическом лице, содержащихся в Едином государственном реестре юридических лиц"
            },
            {
                "Дата": "2022-11-18",
                "Текст": "Изменение сведений о юридическом лице, содержащихся в Едином государственном реестре юридических лиц"
            },
            {
                "Дата": "2020-03-27",
                "Текст": "Представление сведений о выдаче или замене документов, удостоверяющих личность гражданина Российской Федерации на территории Российской Федерации"
            },
            {
                "Дата": "2019-08-07",
                "Текст": "Представление сведений о регистрации юридического лица в качестве страхователя в исполнительном органе Фонда социального страхования Российской Федерации"
            },
            {
                "Дата": "2019-08-06",
                "Текст": "Представление сведений о регистрации юридического лица в качестве страхователя в территориальном органе Пенсионного фонда Российской Федерации"
            },
            {
                "Дата": "2019-08-06",
                "Текст": "Представление сведений о регистрации юридического лица в качестве страхователя в территориальном органе Пенсионного фонда Российской Федерации"
            },
            {
                "Дата": "2019-08-06",
                "Текст": "Представление сведений о регистрации юридического лица в качестве страхователя в исполнительном органе Фонда социального страхования Российской Федерации"
            },
            {
                "Дата": "2019-08-01",
                "Текст": "Представление сведений об учете юридического лица в налоговом органе"
            },
            {
                "Дата": "2019-08-01",
                "Текст": "Представление сведений об учете юридического лица в налоговом органе"
            },
            {
                "Дата": "2019-08-01",
                "Текст": "Государственная регистрация изменений, внесенных в учредительный документ юридического лица, и внесение изменений в сведения о юридическом лице, содержащиеся в ЕГРЮЛ"
            },
            {
                "Дата": "2016-08-17",
                "Текст": "Изменение сведений о юридическом лице, содержащихся в Едином государственном реестре юридических лиц"
            },
            {
                "Дата": "2013-07-22",
                "Текст": "Государственная регистрация изменений, внесенных в учредительный документ юридического лица, и внесение изменений в сведения о юридическом лице, содержащиеся в ЕГРЮЛ"
            },
            {
                "Дата": "2013-06-11",
                "Текст": "Представление сведений о регистрации юридического лица в качестве страхователя в территориальном органе Пенсионного фонда Российской Федерации"
            },
            {
                "Дата": "2013-06-11",
                "Текст": "Представление сведений о регистрации юридического лица в качестве страхователя в исполнительном органе Фонда социального страхования Российской Федерации"
            },
            {
                "Дата": "2013-05-29",
                "Текст": "Представление сведений об учете юридического лица в налоговом органе"
            },
            {
                "Дата": "2013-05-29",
                "Текст": "Создание юридического лица"
            }
        ],
        "ОткрСведения": {
            "КолРаб": "9",
            "СведСНР": "Нет",
            "ПризнУчКГН": "Нет",
            "СумДоход": "869390000",
            "СумРасход": "818173000",
            "Дата": "2025-01-01"
        },
        "История": {
            "Руководитель": {
                "2013-05-29 ~ 2020-03-26": {
                    "ФИОПолн": "Будник Павел Владимирович",
                    "ИННФЛ": "744903252089",
                    "Пол": "Мужской",
                    "ВидГражд": "Гражданин РФ",
                    "Должн": "Генеральный директор"
                }
            },
            "E-mail": {
                "2016-08-17 ~ 2019-07-31": "NOTARY_BARANOVA@MAIL.RU"
            },
            "Адрес": {
                "2013-07-22 ~ 2019-07-31": {
                    "АдресПолн": "обл. Челябинская, г. Челябинск, пр-кт Краснопольский, д.1Д, оф.53"
                }
            },
            "Учредители": [
                {
                    "УчрФЛ": {
                        "ФИОПолн": "Будник Павел Владимирович",
                        "ИННФЛ": "744903252089",
                        "Пол": "Мужской",
                        "ВидГражд": "Гражданин РФ"
                    },
                    "СуммаУК": "7000",
                    "Процент": "70",
                    "Дата": "2013-05-29",
                    "ДатаОконч": "2016-08-17"
                },
                {
                    "УчрФЛ": {
                        "ФИОПолн": "Хохлова Елена Николаевна",
                        "ИННФЛ": "744900114411"
                    },
                    "СуммаУК": "3000",
                    "Процент": "30",
                    "Дата": "2013-05-29",
                    "ДатаОконч": "2016-08-17"
                }
            ],
            "ОткрСведения": [
                {
                    "КолРаб": "10",
                    "СведСНР": "Нет",
                    "ПризнУчКГН": "Нет",
                    "Налоги": [
                        {
                            "НаимНалог": "Страховые взносы на обязательное медицинское страхование работающего населения, зачисляемые в бюджет Федерального фонда обязательного медицинского страхования",
                            "СумУплНал": "102330.74"
                        },
                        {
                            "НаимНалог": "Страховые и другие взносы на обязательное пенсионное страхование, зачисляемые в Пенсионный фонд Российской Федерации",
                            "СумУплНал": "441426.76"
                        },
                        {
                            "НаимНалог": "Страховые взносы на обязательное социальное страхование на случай временной нетрудоспособности и в связи с материнством",
                            "СумУплНал": "56652.37"
                        },
                        {
                            "НаимНалог": "Налог на добавленную стоимость",
                            "СумУплНал": "2298337"
                        },
                        {
                            "НаимНалог": "Налог на прибыль",
                            "СумУплНал": "1693832"
                        },
                        {
                            "НаимНалог": "Налог на имущество организаций",
                            "СумУплНал": "74788"
                        },
                        {
                            "НаимНалог": "Неналоговые доходы, администрируемые налоговыми органами",
                            "СумУплНал": "0"
                        }
                    ],
                    "СумДоход": "203970000",
                    "СумРасход": "172232000",
                    "ОтраслевыеПок": {
                        "НалогНагрузка": "0.03",
                        "Рентабельность": "0.061"
                    },
                    "Дата": "2018-01-01"
                },
                {
                    "КолРаб": "8",
                    "СведСНР": "Нет",
                    "ПризнУчКГН": "Нет",
                    "Налоги": [
                        {
                            "НаимНалог": "Страховые взносы на обязательное медицинское страхование работающего населения, зачисляемые в бюджет Федерального фонда обязательного медицинского страхования",
                            "СумУплНал": "96966.94"
                        },
                        {
                            "НаимНалог": "Страховые и другие взносы на обязательное пенсионное страхование, зачисляемые в Пенсионный фонд Российской Федерации",
                            "СумУплНал": "418288.72"
                        },
                        {
                            "НаимНалог": "Страховые взносы на обязательное социальное страхование на случай временной нетрудоспособности и в связи с материнством",
                            "СумУплНал": "45765.11"
                        },
                        {
                            "НаимНалог": "Налог на добавленную стоимость",
                            "СумУплНал": "5488421"
                        },
                        {
                            "НаимНалог": "Налог на прибыль",
                            "СумУплНал": "7147668"
                        },
                        {
                            "НаимНалог": "Транспортный налог",
                            "СумУплНал": "1425"
                        },
                        {
                            "НаимНалог": "Налог на имущество организаций",
                            "СумУплНал": "0"
                        },
                        {
                            "НаимНалог": "Неналоговые доходы, администрируемые налоговыми органами",
                            "СумУплНал": "0"
                        }
                    ],
                    "СумДоход": "219231000",
                    "СумРасход": "208432000",
                    "ОтраслевыеПок": {
                        "НалогНагрузка": "0.027",
                        "Рентабельность": "0.1"
                    },
                    "Дата": "2019-01-01"
                },
                {
                    "КолРаб": "8",
                    "СведСНР": "Нет",
                    "ПризнУчКГН": "Нет",
                    "Налоги": [
                        {
                            "НаимНалог": "Страховые взносы на обязательное медицинское страхование работающего населения, зачисляемые в бюджет Федерального фонда обязательного медицинского страхования",
                            "СумУплНал": "103890.12"
                        },
                        {
                            "НаимНалог": "Страховые и другие взносы на обязательное пенсионное страхование, зачисляемые в Пенсионный фонд Российской Федерации",
                            "СумУплНал": "448153.42"
                        },
                        {
                            "НаимНалог": "Страховые взносы на обязательное социальное страхование на случай временной нетрудоспособности и в связи с материнством",
                            "СумУплНал": "59074.77"
                        },
                        {
                            "НаимНалог": "Налог на добавленную стоимость",
                            "СумУплНал": "6513987"
                        },
                        {
                            "НаимНалог": "Налог на прибыль",
                            "СумУплНал": "6966307"
                        },
                        {
                            "НаимНалог": "Транспортный налог",
                            "СумУплНал": "8552"
                        },
                        {
                            "НаимНалог": "Налог на имущество организаций",
                            "СумУплНал": "0"
                        },
                        {
                            "НаимНалог": "Неналоговые доходы, администрируемые налоговыми органами",
                            "СумУплНал": "0"
                        }
                    ],
                    "СумДоход": "272977000",
                    "СумРасход": "238970000",
                    "ОтраслевыеПок": {
                        "НалогНагрузка": "0.025",
                        "Рентабельность": "0.083"
                    },
                    "Дата": "2020-01-01"
                },
                {
                    "КолРаб": "8",
                    "СведСНР": "Нет",
                    "ПризнУчКГН": "Нет",
                    "Налоги": [
                        {
                            "НаимНалог": "Страховые взносы на обязательное медицинское страхование работающего населения, зачисляемые в бюджет Федерального фонда обязательного медицинского страхования",
                            "СумУплНал": "483484.27"
                        },
                        {
                            "НаимНалог": "Страховые и другие взносы на обязательное пенсионное страхование, зачисляемые в Пенсионный фонд Российской Федерации",
                            "СумУплНал": "1126200.69"
                        },
                        {
                            "НаимНалог": "Страховые взносы на обязательное социальное страхование на случай временной нетрудоспособности и в связи с материнством",
                            "СумУплНал": "34671.36"
                        },
                        {
                            "НаимНалог": "Налог на добавленную стоимость",
                            "СумУплНал": "11249840"
                        },
                        {
                            "НаимНалог": "Налог на прибыль",
                            "СумУплНал": "7052338"
                        },
                        {
                            "НаимНалог": "Транспортный налог",
                            "СумУплНал": "18989"
                        },
                        {
                            "НаимНалог": "Налог на имущество организаций",
                            "СумУплНал": "0"
                        },
                        {
                            "НаимНалог": "Неналоговые доходы, администрируемые налоговыми органами",
                            "СумУплНал": "0"
                        }
                    ],
                    "СумДоход": "225918",
                    "СумРасход": "206557",
                    "ОтраслевыеПок": {
                        "НалогНагрузка": "0.026294028",
                        "Рентабельность": "0.054"
                    },
                    "Дата": "2021-01-01"
                },
                {
                    "КолРаб": "7",
                    "СведСНР": "Нет",
                    "ПризнУчКГН": "Нет",
                    "Налоги": [
                        {
                            "НаимНалог": "Страховые взносы на обязательное медицинское страхование работающего населения, зачисляемые в бюджет Федерального фонда обязательного медицинского страхования",
                            "СумУплНал": "1084211.61",
                            "СумНедНалог": "0",
                            "СумПени": "1.64",
                            "СумШтраф": "0",
                            "ОбщСумНедоим": "1.64"
                        },
                        {
                            "НаимНалог": "Страховые и другие взносы на обязательное пенсионное страхование, зачисляемые в Пенсионный фонд Российской Федерации",
                            "СумУплНал": "2520129.46"
                        },
                        {
                            "НаимНалог": "Страховые взносы на обязательное социальное страхование на случай временной нетрудоспособности и в связи с материнством",
                            "СумУплНал": "22735.16"
                        },
                        {
                            "НаимНалог": "Налог на добавленную стоимость",
                            "СумУплНал": "8034399"
                        },
                        {
                            "НаимНалог": "Налог на прибыль",
                            "СумУплНал": "8637771"
                        },
                        {
                            "НаимНалог": "Транспортный налог",
                            "СумУплНал": "17766"
                        },
                        {
                            "НаимНалог": "Налог на имущество организаций",
                            "СумУплНал": "0"
                        },
                        {
                            "НаимНалог": "Неналоговые доходы, администрируемые налоговыми органами",
                            "СумУплНал": "0"
                        }
                    ],
                    "СумДоход": "321874000",
                    "СумРасход": "280486000",
                    "ОтраслевыеПок": {
                        "НалогНагрузка": "0.021230691",
                        "Рентабельность": "0.105"
                    },
                    "Дата": "2022-01-01"
                },
                {
                    "КолРаб": "8",
                    "СведСНР": "Нет",
                    "ПризнУчКГН": "Нет",
                    "Налоги": [
                        {
                            "НаимНалог": "Страховые взносы на обязательное медицинское страхование работающего населения, зачисляемые в бюджет Федерального фонда обязательного медицинского страхования",
                            "СумУплНал": "1905441.01"
                        },
                        {
                            "НаимНалог": "Страховые и другие взносы на обязательное пенсионное страхование, зачисляемые в Пенсионный фонд Российской Федерации",
                            "СумУплНал": "3693507.57"
                        },
                        {
                            "НаимНалог": "Страховые взносы на обязательное социальное страхование на случай временной нетрудоспособности и в связи с материнством",
                            "СумУплНал": "28449.94"
                        },
                        {
                            "НаимНалог": "Налог на добавленную стоимость",
                            "СумУплНал": "16848158"
                        },
                        {
                            "НаимНалог": "Налог на прибыль",
                            "СумУплНал": "11439189"
                        },
                        {
                            "НаимНалог": "Транспортный налог",
                            "СумУплНал": "12546"
                        },
                        {
                            "НаимНалог": "Налог на имущество организаций",
                            "СумУплНал": "0"
                        },
                        {
                            "НаимНалог": "Неналоговые доходы, администрируемые налоговыми органами",
                            "СумУплНал": "0"
                        }
                    ],
                    "СумДоход": "599967000",
                    "СумРасход": "528425000",
                    "ОтраслевыеПок": {
                        "НалогНагрузка": "0.030650462",
                        "Рентабельность": "0.101"
                    },
                    "Дата": "2023-01-01"
                },
                {
                    "КолРаб": "9",
                    "СведСНР": "Нет",
                    "ПризнУчКГН": "Нет",
                    "Налоги": [
                        {
                            "НаимНалог": "Страховые взносы на обязательное медицинское страхование работающего населения, зачисляемые в бюджет Федерального фонда обязательного медицинского страхования",
                            "СумУплНал": "0"
                        },
                        {
                            "НаимНалог": "Страховые и другие взносы на обязательное пенсионное страхование, зачисляемые в Пенсионный фонд Российской Федерации",
                            "СумУплНал": "5513271.92"
                        },
                        {
                            "НаимНалог": "Страховые взносы на обязательное социальное страхование на случай временной нетрудоспособности и в связи с материнством",
                            "СумУплНал": "0"
                        },
                        {
                            "НаимНалог": "Налог на добавленную стоимость",
                            "СумУплНал": "14183212"
                        },
                        {
                            "НаимНалог": "Налог на прибыль",
                            "СумУплНал": "24146522.99"
                        },
                        {
                            "НаимНалог": "Транспортный налог",
                            "СумУплНал": "12810"
                        },
                        {
                            "НаимНалог": "Налог на имущество организаций",
                            "СумУплНал": "4978"
                        },
                        {
                            "НаимНалог": "Земельный налог",
                            "СумУплНал": "15837"
                        },
                        {
                            "НаимНалог": "Суммы пеней",
                            "СумУплНал": "0"
                        }
                    ],
                    "СумДоход": "742614000",
                    "СумРасход": "703330000",
                    "ОтраслевыеПок": {
                        "НалогНагрузка": "0.035",
                        "Рентабельность": "0.051"
                    },
                    "Дата": "2024-01-01"
                }
            ]
        }
    }
}